sixty/__init__.py
sixty/sixty.py
sixty-0.1.dist-info/LICENSE
sixty-0.1.dist-info/METADATA
sixty-0.1.dist-info/WHEEL
sixty-0.1.dist-info/top_level.txt
sixty-0.1.dist-info/RECORD
