Metadata-Version: 2.1
Name: sixty
Version: 0.1
Summary: Python wrapper for SIXTE
Home-page: https://github.com/ruizca/sixty
Author: Angel Ruiz
Author-email: angel.ruizca@gmail.com
License: UNKNOWN
Platform: UNKNOWN
Classifier: Development Status :: 4 - Beta
Classifier: Intended Audience :: Science/Research
Classifier: Topic :: Scientific/Engineering :: Astronomy
Classifier: Programming Language :: Python :: 3
Classifier: License :: OSI Approved :: BSD License
Classifier: Operating System :: POSIX :: Linux
Requires-Python: >=3.6
License-File: LICENSE
